dac/__init__.py
dac/_cli.py
dac/_file_helper.py
dac/_packing.py
dac/_pyproject_factory.py
dac/_version_management.py
dac/_input/__init__.py
dac/_input/config.py
dac/_input/interface.py
dac/_input/pyproject.py
dac-0.4.3.dist-info/licenses/LICENSE
dac-0.4.3.dist-info/METADATA
dac-0.4.3.dist-info/WHEEL
dac-0.4.3.dist-info/entry_points.txt
dac-0.4.3.dist-info/top_level.txt
dac-0.4.3.dist-info/RECORD
