Metadata-Version: 2.4
Name: dac
Version: 0.4.3
Summary: Tool to distribute data as code
Author-email: Francesco Calcavecchia <francesco.calcavecchia@gmail.com>
Maintainer-email: Francesco Calcavecchia <francesco.calcavecchia@gmail.com>
License: MIT
Project-URL: homepage, https://data-as-code.github.io/dac/
Project-URL: documentation, https://data-as-code.github.io/dac/
Project-URL: repository, https://github.com/data-as-code/dac
Project-URL: changelog, https://github.com/data-as-code/dac/blob/main/CHANGELOG.md
Classifier: Programming Language :: Python :: 3
Classifier: Development Status :: 3 - Alpha
Classifier: Intended Audience :: Developers
Classifier: Topic :: Software Development :: Build Tools
Classifier: License :: OSI Approved :: MIT License
Classifier: Topic :: Scientific/Engineering
Classifier: Operating System :: OS Independent
Requires-Python: <3.14,>=3.9
License-File: LICENSE
Requires-Dist: build~=1.2
Requires-Dist: toml~=0.10.2
Requires-Dist: typer~=0.15.2
Requires-Dist: wheel~=0.45
Dynamic: license-file
